django_trello_webhooks-0.3.dist-info/DESCRIPTION.rst
django_trello_webhooks-0.3.dist-info/METADATA
django_trello_webhooks-0.3.dist-info/metadata.json
django_trello_webhooks-0.3.dist-info/RECORD
django_trello_webhooks-0.3.dist-info/top_level.txt
django_trello_webhooks-0.3.dist-info/WHEEL
trello_webhooks/__init__.py
trello_webhooks/admin.py
trello_webhooks/forms.py
trello_webhooks/models.py
trello_webhooks/settings.py
trello_webhooks/signals.py
trello_webhooks/urls.py
trello_webhooks/views.py
trello_webhooks/management/__init__.py
trello_webhooks/management/commands/__init__.py
trello_webhooks/management/commands/sync_webhooks.py
trello_webhooks/migrations/0001_initial.py
trello_webhooks/migrations/0002_webhook_is_active.py
trello_webhooks/migrations/__init__.py
trello_webhooks/templates/.DS_Store
trello_webhooks/templates/admin/trello_webhooks/webhook/change_form.html
trello_webhooks/templates/trello_webhooks/addChecklistToCard.html
trello_webhooks/templates/trello_webhooks/commentCard.html
trello_webhooks/templates/trello_webhooks/createCheckItem.html
trello_webhooks/templates/trello_webhooks/deleteCheckItem.html
trello_webhooks/templates/trello_webhooks/updateCard.html
trello_webhooks/templates/trello_webhooks/updateCheckItem.html
trello_webhooks/templates/trello_webhooks/updateCheckItemStateOnCard.html
trello_webhooks/templates/trello_webhooks/updateComment.html
trello_webhooks/templates/trello_webhooks/updateList.html
trello_webhooks/templates/trello_webhooks/partials/update_values_list.html
trello_webhooks/templatetags/__init__.py
trello_webhooks/templatetags/trello_webhook_tags.py
trello_webhooks/tests/__init__.py
trello_webhooks/tests/test_admin.py
trello_webhooks/tests/test_models.py
trello_webhooks/tests/test_templatetags.py
trello_webhooks/tests/test_views.py
trello_webhooks/tests/sample_data/commentCard.json
trello_webhooks/tests/sample_data/createCard.json
trello_webhooks/tests/sample_data/createList.json
trello_webhooks/tests/sample_data/updateCard.json
trello_webhooks/tests/sample_data/updateComment.json
