Metadata-Version: 2.0
Name: django-trello-webhooks
Version: 0.3
Summary: Django Trello Webhooks - Trello callback integration for Django.
Home-page: https://github.com/yunojuno/django-trello-webhooks
Author: Hugo Rodger-Brown
Author-email: hugo@yunojuno.com
License: UNKNOWN
Platform: UNKNOWN
Classifier: Environment :: Web Environment
Classifier: Framework :: Django
Classifier: Intended Audience :: Developers
Classifier: License :: OSI Approved :: MIT License
Classifier: Operating System :: OS Independent
Classifier: Programming Language :: Python
Classifier: Programming Language :: Python :: 2.7
Classifier: Topic :: Internet :: WWW/HTTP
Classifier: Topic :: Internet :: WWW/HTTP :: Dynamic Content
Requires-Dist: django (>=1.7.1)
